mydf/__init__.py
mydf/mydatafs.py
mydataframesales-0.0.1.dist-info/LICENSE
mydataframesales-0.0.1.dist-info/METADATA
mydataframesales-0.0.1.dist-info/WHEEL
mydataframesales-0.0.1.dist-info/top_level.txt
mydataframesales-0.0.1.dist-info/RECORD
