Metadata-Version: 2.1
Name: mydataframesales
Version: 0.0.1
Summary: Functions for sales.
Home-page: https://github.com/pypa/myDataFrameSales
Author: Pascale Gregorio
Author-email: gregoriopascale@gmail.com
License: UNKNOWN
Platform: UNKNOWN
Classifier: Programming Language :: Python :: 3
Classifier: License :: OSI Approved :: MIT License
Classifier: Operating System :: OS Independent
Requires-Python: >=3.6
